mist/__init__.py
mist/version.py
mist/app/__init__.py
mist/app/errors.py
mist/app/model.py
mist/app/dbs/__init__.py
mist/app/dbs/basedownloader.py
mist/app/dbs/bigsdbauthdownloader.py
mist/app/dbs/bigsdbdownloader.py
mist/app/dbs/cgmlstorgdownloader.py
mist/app/dbs/enterobasedownloader.py
mist/app/loggers/__init__.py
mist/app/loggers/logger.py
mist/app/query/__init__.py
mist/app/query/allelequeryminimap.py
mist/app/query/bestmatching.py
mist/app/query/profilequery.py
mist/app/query/seqholder.py
mist/app/utils/__init__.py
mist/app/utils/clustersplit.py
mist/app/utils/clusterutils.py
mist/app/utils/command.py
mist/app/utils/dbutils.py
mist/app/utils/dependencies.py
mist/app/utils/minimap2utils.py
mist/app/utils/nucmerutils.py
mist/app/utils/restutils.py
mist/app/utils/sequenceutils.py
mist/app/utils/testingutils.py
mist/resources/citation.txt
mist/resources/pubmlst/download_bigsdb.py
mist/resources/testdata/NEIS0140-fmt.fasta
mist/resources/testdata/NEIS0140-subset.fasta
mist/resources/testdata/NEIS0159-subset.fasta
mist/resources/testdata/query-both_absent.fasta
mist/resources/testdata/query-edge.fasta
mist/resources/testdata/query-multi_hit.fasta
mist/resources/testdata/query-novel.fasta
mist/resources/testdata/query-novel_rc.fasta
mist/resources/testdata/query-one_absent.fasta
mist/resources/testdata/query-perfect_hits.fasta
mist/resources/testdata/output/GCF_000010485.1.json
mist/resources/testdata/output/GCF_000010485.1.tsv
mist/resources/testdata/output/GCF_025995355.1.json
mist/resources/testdata/output/GCF_025995355.1.tsv
mist/resources/testdata/output/GCF_026016785.1.json
mist/resources/testdata/output/GCF_026016785.1.tsv
mist/resources/testdata/output/GCF_036419615.1.json
mist/resources/testdata/output/GCF_036419615.1.tsv
mist/scripts/__init__.py
mist/scripts/cli.py
mist/scripts/mistcaller.py
mist/scripts/mistdists.py
mist/scripts/mistdownload.py
mist/scripts/mistindex.py
mist/scripts/mistlist.py
mist/scripts/various/__init__.py
mist_typing-1.1.0.dist-info/licenses/LICENSE
mist_typing-1.1.0.dist-info/METADATA
mist_typing-1.1.0.dist-info/WHEEL
mist_typing-1.1.0.dist-info/entry_points.txt
mist_typing-1.1.0.dist-info/top_level.txt
mist_typing-1.1.0.dist-info/RECORD
