Metadata-Version: 2.4
Name: mist_typing
Version: 1.1.0
Summary: multi-locus sequence typing (MLST) and cgMLST
Author-email: Bert Bogaerts <bioit@sciensano.be>
License-Expression: GPL-3.0-or-later
Project-URL: Homepage, https://github.com/BioinformaticsPlatformWIV-ISP/MiST
Project-URL: Issues, https://github.com/BioinformaticsPlatformWIV-ISP/MiST/issues
Keywords: typing,mlst,phylogeny
Classifier: Development Status :: 4 - Beta
Classifier: Intended Audience :: Science/Research
Classifier: Topic :: Scientific/Engineering :: Bio-Informatics
Classifier: Programming Language :: Python :: 3
Requires-Python: >=3
License-File: LICENSE
Requires-Dist: biopython
Requires-Dist: bs4
Requires-Dist: click
Requires-Dist: furl
Requires-Dist: pandas
Requires-Dist: pytest
Requires-Dist: pytest-xdist
Requires-Dist: rauth
Requires-Dist: requests
Dynamic: license-file
